lins_dbrouters/__init__.py
lins_dbrouters/dbrouters.py
lins_dbrouters-0.3.0.7.dist-info/METADATA
lins_dbrouters-0.3.0.7.dist-info/WHEEL
lins_dbrouters-0.3.0.7.dist-info/top_level.txt
lins_dbrouters-0.3.0.7.dist-info/RECORD
